[{
    "title": "Blog",
    "content": "VMac Writes is hosted on Wordpress.com and has more than 100 blog posts. From Cloud to AI to Gaming.",
    "imgUrl": "/static/images/cards/drop.jpg",
    "more": "https://vmacwrites.wordpress.com/"
  },
  {
    "title": "Medium",
    "content": "Interesting and important technical thoughts are posted here for your reference. Clap if you like and also check my claps. #AI #ML ",
    "imgUrl": "/static/images/cards/docks.jpg",
    "more": "https://medium.com/@VidyasagarMSC"
  },
  {
    "title": "DZone",
    "content": "DZone Most Valuable Blogger | A collection of my technical articles. Catering Cloud, Cognitive, and many more...",
    "imgUrl": "https://vmacwrites.files.wordpress.com/2017/04/cropped-cropped-qtq80-tbq9tn-4.jpeg",
    "more": "https://dzone.com/users/2567192/vidyasagarmsc.html"
  }]